README.rst
setup.cfg
setup.py
cyclotron_consul/__init__.py
cyclotron_consul/kv.py
cyclotron_consul.egg-info/PKG-INFO
cyclotron_consul.egg-info/SOURCES.txt
cyclotron_consul.egg-info/dependency_links.txt
cyclotron_consul.egg-info/requires.txt
cyclotron_consul.egg-info/top_level.txt