Metadata-Version: 1.2
Name: cyclotron-consul
Version: 0.1.0
Summary: A consul adapter for cyclotron
Home-page: https://github.com/mainro/cyclotron_consul.git
Author: Romain Picard
Author-email: romain.picard@oakbits.com
License: MIT
Project-URL: Documentation, https://cyclotron-consul.readthedocs.io
Platform: any
Classifier: Development Status :: 3 - Alpha
Classifier: License :: OSI Approved :: MIT License
Classifier: Intended Audience :: Developers
Classifier: Programming Language :: Python :: 3
